tno/quantum/ml/components/__init__.py
tno/quantum/ml/components/_qubo_estimator.py
tno/quantum/ml/components/_serialization.py
tno/quantum/ml/components/py.typed
tno/quantum/ml/components/test/__init__.py
tno/quantum/ml/components/test/test_qubo_estimator.py
tno_quantum_ml_components-2.0.3.dist-info/licenses/LICENSE
tno_quantum_ml_components-2.0.3.dist-info/METADATA
tno_quantum_ml_components-2.0.3.dist-info/WHEEL
tno_quantum_ml_components-2.0.3.dist-info/top_level.txt
tno_quantum_ml_components-2.0.3.dist-info/RECORD
